pedumper/__init__.py
pedumper/cli.py
pedumper/defines.py
pedumper/winapi.py
pedumper-1.2.0.dist-info/LICENSE
pedumper-1.2.0.dist-info/METADATA
pedumper-1.2.0.dist-info/WHEEL
pedumper-1.2.0.dist-info/entry_points.txt
pedumper-1.2.0.dist-info/top_level.txt
pedumper-1.2.0.dist-info/RECORD
