Metadata-Version: 2.1
Name: pedumper
Version: 1.2.0
Summary: Dumper can easily extract PE files in the memory of the target process
Author-email: Chihiro Hasegawa <encry1024@gmail.com>
License: Copyright © 2022 Chihiro Hasegawa
License-File: LICENSE
Requires-Dist: pefile
Provides-Extra: dev
Requires-Dist: pyproject-flake8 ; extra == 'dev'
Requires-Dist: flake8 ; extra == 'dev'
Requires-Dist: black ; extra == 'dev'
Requires-Dist: isort ; extra == 'dev'
